<?xml version="1.0" encoding="UTF-8"?><items iblockUid="content:technology" exchangeVersion="2"><item><field name="ACTIVE"><value>Y</value></field><field name="ACTIVE_FROM"/><field name="ACTIVE_TO"/><field name="SORT"><value>500</value></field><field name="NAME"><value>Технология 1</value></field><field name="PREVIEW_PICTURE"><value name="1.jpg">iblock/052/hna9o1b7iwecpec07nnjeu6fiscvq4i7.jpg</value></field><field name="PREVIEW_TEXT"/><field name="PREVIEW_TEXT_TYPE"><value>text</value></field><field name="DETAIL_PICTURE"/><field name="DETAIL_TEXT"/><field name="DETAIL_TEXT_TYPE"><value>text</value></field><field name="CODE"><value>tekhnologiya-1</value></field><field name="TAGS"/><field name="XML_ID"><value>12179</value></field><field name="IBLOCK_SECTION"/><property name="VIDEO"><value name="1.mp4">iblock/fe4/kxl0zilvo42k2jxknejd3cfbaii8h7mm.mp4</value><value name="2.mp4">iblock/9a2/6i74mdkw92biupydztahgwfku2wqsdg7.mp4</value><value name="3.mp4">iblock/8d9/0juiy6jzdkmf2hnu1eb0pjq46kh6cvxp.mp4</value><value name="4.mp4">iblock/dd7/anzv0njfu433zd058igmphxxhs2j0in5.mp4</value><value name="5.mp4">iblock/612/1ajwd4eb5vgj6oi6zlld4syn3ul7e6wq.mp4</value><value name="6.mp4">iblock/c50/m9311pfzjcim7c2669ieshi194iiv02q.mp4</value><value name="7.mp4">iblock/29f/z41ahki14cpqh4646pyg9xg5zwzr0gch.mp4</value><value name="8.mp4">iblock/861/dyl3c9f9fcsjmky6s9rzohf23ge09x81.mp4</value></property><property name="STAGES"><value>Фасад</value><value>Фундамент</value><value>Опора</value><value>Силовой&amp;lt;br&amp;gt;каркас</value><value>Вторичный&amp;lt;br&amp;gt;каркас</value><value>Водоотлив</value><value>Стык&amp;lt;br&amp;gt;панелей</value><value>Окно</value><value>Ворота</value></property></item><item><field name="ACTIVE"><value>Y</value></field><field name="ACTIVE_FROM"/><field name="ACTIVE_TO"/><field name="SORT"><value>500</value></field><field name="NAME"><value>Технология 2</value></field><field name="PREVIEW_PICTURE"><value name="1.jpg">iblock/59c/dxpup1uikhri05jv7qnckcuumxefr1yw.jpg</value></field><field name="PREVIEW_TEXT"/><field name="PREVIEW_TEXT_TYPE"><value>text</value></field><field name="DETAIL_PICTURE"/><field name="DETAIL_TEXT"/><field name="DETAIL_TEXT_TYPE"><value>text</value></field><field name="CODE"><value>tekhnologiya-2</value></field><field name="TAGS"/><field name="XML_ID"><value>12180</value></field><field name="IBLOCK_SECTION"/><property name="VIDEO"><value name="2_0.mp4">iblock/31a/p2h1yeo9cuawdb1vb1kwtip9491lg7i0.mp4</value><value name="2_1.mp4">iblock/12f/xtomyavc5vgnbuoxr9p2gips7gs1mzpk.mp4</value><value name="2_2.mp4">iblock/474/146b61ak9qqvatfu1w4pno41wmzsr6i5.mp4</value><value name="2_3.mp4">iblock/6f0/4gmgnt20i9nh9lnh1aiysxu0klkx83m9.mp4</value><value name="2_4.mp4">iblock/074/biodln7i4gvs1k8bvt3kajenwxqlad4l.mp4</value><value name="2_5.mp4">iblock/904/hr25kukucld2v327ej07d74fuaii68d1.mp4</value><value name="2_6.mp4">iblock/bec/pooivxksfkau1ji46tvadibau9g2q6yc.mp4</value><value name="2_7.mp4">iblock/40a/9bvwlvla9ee79bgsbw89pcje3mjf6anw.mp4</value><value name="2_8.mp4">iblock/694/9q263oujflfyb7vi2i02qx13sf5vhodo.mp4</value><value name="2_9.mp4">iblock/9e6/3xv1znp0e70efkaayjv9lin2lp8og00b.mp4</value><value name="2_10.mp4">iblock/92d/9iyqbk9s2i9z6oksikcwm8nuscgmj3vp.mp4</value></property><property name="STAGES"><value>Tab 9</value><value>Tab 10</value><value>Tab 11</value><value>Tab 12</value><value>Tab 13</value><value>Tab 14</value><value>Tab 15</value><value>Tab 16</value><value>Tab 17</value><value>Tab 18</value><value>Tab 19</value><value>Tab 20</value><value>Tab 21</value><value>Tab 22</value></property></item></items>